tiktok_username_finder/__init__.py
tiktok_username_finder-0.1.0.dist-info/METADATA
tiktok_username_finder-0.1.0.dist-info/WHEEL
tiktok_username_finder-0.1.0.dist-info/top_level.txt
tiktok_username_finder-0.1.0.dist-info/RECORD
