Metadata-Version: 2.1
Name: tiktok-username-finder
Version: 0.1.0
Summary: A Python library to find TikTok usernames by email
Home-page: https://github.com/yourusername/tiktok-username-finder
Author: Your Name
Author-email: your.email@example.com
License: UNKNOWN
Platform: UNKNOWN
Classifier: Programming Language :: Python :: 3
Classifier: License :: OSI Approved :: MIT License
Classifier: Operating System :: OS Independent
Requires-Python: >=3.6
Requires-Dist: SignerPy
Requires-Dist: requests
